dsc/__init__.py
dsc/client.py
dsc/enums.py
dsc/models.py
dsc.py-1.1.3.dist-info/LICENSE
dsc.py-1.1.3.dist-info/METADATA
dsc.py-1.1.3.dist-info/WHEEL
dsc.py-1.1.3.dist-info/top_level.txt
dsc.py-1.1.3.dist-info/RECORD
