Metadata-Version: 2.1
Name: dsc.py
Version: 1.1.3
Summary: A simple and easy to use, fully asynchronous wrapper for the dsc.gg API.
Home-page: https://github.com/itsmewulf/dsc.py
Author: itsmewulf
Author-email: wulf.developer@gmail.com
License: UNKNOWN
Keywords: api-wrapper,http,request,api,wrapper,discord
Platform: UNKNOWN
Classifier: Programming Language :: Python :: 3
Classifier: License :: OSI Approved :: MIT License
Classifier: Operating System :: OS Independent
Requires-Python: >=3.7
